spchat/__init__.py
spchat/avatars.py
spchat/chat.py
spchat/filters.py
spchat/prompts.py
spchat/retrievers.py
spchat/session.py
spchat/stage.py
spchat/utils.py
spchat/gradio/components.py
spchat/gradio/models.py
spchat/gradio/common/anonymous.py
spchat/templates/__init__.py
spchat/templates/ca.py
spchat/templates/stability.py
spchat/templates/unique.py
spchat-0.2.0.dist-info/METADATA
spchat-0.2.0.dist-info/WHEEL
spchat-0.2.0.dist-info/top_level.txt
spchat-0.2.0.dist-info/RECORD
