Metadata-Version: 2.1
Name: spchat
Version: 0.2.0
Summary: Chat utility library by Spiral.AI
Author-email: ksterx <kostonerx@gmail.com>
Classifier: Programming Language :: Python :: 3
Requires-Python: >=3.10
Requires-Dist: chromadb
Requires-Dist: loguru
Requires-Dist: openai
Requires-Dist: pandas
Provides-Extra: dev
Requires-Dist: pytest ; extra == 'dev'
Requires-Dist: ruff ; extra == 'dev'
Provides-Extra: gpu
Requires-Dist: flash-attn ; extra == 'gpu'
